CHANGES.rst
LICENSE
MANIFEST.in
README.rst
setup.cfg
setup.py
tox.ini
sphinxcontrib/__init__.py
sphinxcontrib/exampleblock.css
sphinxcontrib/exampleblock.js
sphinxcontrib/exampleblock.py
sphinxcontrib_exampleblock.egg-info/PKG-INFO
sphinxcontrib_exampleblock.egg-info/SOURCES.txt
sphinxcontrib_exampleblock.egg-info/dependency_links.txt
sphinxcontrib_exampleblock.egg-info/namespace_packages.txt
sphinxcontrib_exampleblock.egg-info/not-zip-safe
sphinxcontrib_exampleblock.egg-info/requires.txt
sphinxcontrib_exampleblock.egg-info/top_level.txt